smartframe/__init__.py
smartframe/core.py
smartframe/storage.py
smartframe/utils.py
smartframe_df-0.1.0.dist-info/METADATA
smartframe_df-0.1.0.dist-info/WHEEL
smartframe_df-0.1.0.dist-info/top_level.txt
smartframe_df-0.1.0.dist-info/RECORD
