Metadata-Version: 2.4
Name: smartframe-df
Version: 0.1.0
Summary: Memory-efficient DataFrame management - auto-offload to disk
Author: SmartFrame
License: MIT
Project-URL: Homepage, https://github.com/smartframe/smartframe
Project-URL: Documentation, https://github.com/smartframe/smartframe#readme
Keywords: pandas,dataframe,memory,big-data,jupyter
Classifier: Development Status :: 3 - Alpha
Classifier: Intended Audience :: Developers
Classifier: Intended Audience :: Science/Research
Classifier: License :: OSI Approved :: MIT License
Classifier: Programming Language :: Python :: 3
Classifier: Programming Language :: Python :: 3.8
Classifier: Programming Language :: Python :: 3.9
Classifier: Programming Language :: Python :: 3.10
Classifier: Programming Language :: Python :: 3.11
Classifier: Programming Language :: Python :: 3.12
Classifier: Topic :: Scientific/Engineering
Requires-Python: >=3.8
Requires-Dist: pandas>=1.3.0
Requires-Dist: pyarrow>=7.0.0
Requires-Dist: numpy>=1.20.0
Provides-Extra: dev
Requires-Dist: pytest>=7.0.0; extra == "dev"
Requires-Dist: pytest-cov>=3.0.0; extra == "dev"
